cellreel/__init__.py
cellreel/__main__.py
cellreel/_version.py
cellreel/_version_save.py
cellreel/crosshair.py
cellreel/dlg_open.py
cellreel/helper.py
cellreel/main.py
cellreel/spacing.py
cellreel/tab_info.py
cellreel/tab_reco.py
cellreel/tab_sino.py
cellreel-0.1.0.dist-info/LICENSE
cellreel-0.1.0.dist-info/METADATA
cellreel-0.1.0.dist-info/WHEEL
cellreel-0.1.0.dist-info/top_level.txt
cellreel-0.1.0.dist-info/RECORD
